med_self_discover/__init__.py
med_self_discover/modules.py
med_self_discover/self_discover.py
med_self_discover-0.1.4.dist-info/METADATA
med_self_discover-0.1.4.dist-info/WHEEL
med_self_discover-0.1.4.dist-info/top_level.txt
med_self_discover-0.1.4.dist-info/RECORD
