Metadata-Version: 2.1
Name: med-self-discover
Version: 0.1.4
Summary: Implementation of the Code from the Paper SELF-DISCOVER: Large Language Models Self-Compose Reasoning Structures,
Home-page: https://github.com/Dyke-F/medical-self-discover
Author: Dyke Ferber
Author-email: dykeferber@gmail.com
License: MIT
Keywords: Large Language Models,Self Prompting,Medical LLM Prompting,LLMs for Medicine
Requires-Dist: openai >=1.12.0
Requires-Dist: tenacity >=8.2.3
Requires-Dist: fire >=0.5.0
Requires-Dist: termcolor >=2.4.0
